aircraft_carrier/__init__.py
aircraft_carrier-0.0.1.dist-info/LICENSE
aircraft_carrier-0.0.1.dist-info/METADATA
aircraft_carrier-0.0.1.dist-info/WHEEL
aircraft_carrier-0.0.1.dist-info/top_level.txt
aircraft_carrier-0.0.1.dist-info/RECORD
