Metadata-Version: 2.1
Name: aircraft-carrier
Version: 0.0.1
Summary: Booster for Web Project Carriers in Universities
Home-page: https://github.com/fybmain/AircraftCarrier
Author: fyb
Author-email: fybmain@gmail.com
License: UNKNOWN
Platform: UNKNOWN
Classifier: Programming Language :: Python :: 3
Classifier: License :: OSI Approved :: MIT License
Classifier: Operating System :: OS Independent
